nefis/nefis.pyd
nefis/__init__.py
nefis-0.2.1.data/data/msvcr110.dll
nefis-0.2.1.data/data/nefis.dll
nefis-0.2.1.data/data/trim-f34.dat
nefis-0.2.1.data/data/trim-f34.def
nefis-0.2.1.dist-info/DESCRIPTION.rst
nefis-0.2.1.dist-info/METADATA
nefis-0.2.1.dist-info/metadata.json
nefis-0.2.1.dist-info/RECORD
nefis-0.2.1.dist-info/top_level.txt
nefis-0.2.1.dist-info/WHEEL
tests/nefis_attributes.py
tests/nefis_define.py
tests/nefis_doc_strings.py
tests/nefis_getels_strings.py
tests/nefis_getelt_floats.py
tests/nefis_getelt_integers.py
tests/nefis_get_headers.py
tests/nefis_inquire.py
tests/nefis_putels_strings.py
tests/nefis_putelt_floats.py
tests/nefis_putelt_integers.py
tests/__init__.py
