Metadata-Version: 2.0
Name: nefis
Version: 0.2.1
Summary: NEFIS library
Home-page: http://oss.deltares.nl/web/delft3d
Author: Jan Mooiman
Author-email: jan.mooiman@deltares.nl
License: LGPLv3
Keywords: nefis file_format
Platform: UNKNOWN
Classifier: Development Status :: 4 - Beta
Classifier: Intended Audience :: Developers
Classifier: Intended Audience :: Science/Research
Classifier: Topic :: Scientific/Engineering
Classifier: License :: OSI Approved :: GNU Lesser General Public License v3 (LGPLv3)
Classifier: Programming Language :: Python :: 2.7
Classifier: Operating System :: Microsoft :: Windows
